aes_sha1prng/__init__.py
aes_sha1prng/aes.py
aes_sha1prng-0.0.2.dist-info/METADATA
aes_sha1prng-0.0.2.dist-info/RECORD
aes_sha1prng-0.0.2.dist-info/WHEEL
aes_sha1prng-0.0.2.dist-info/top_level.txt
aes_sha1prng-0.0.2.dist-info/zip-safe
